{
    "$schema": "./schema/v1.json",
    "name": "マクドナルド",
    "date": "2022-02-13",
    "menus": [
        {
            "name": "肉厚ビーフバーガー ペッパー&チーズ"
        },
        {
            "name": "肉厚ビーフバーガー ペッパー&チーズ",
            "calories": 503
        },
        {
            "name": "グリルチキンバーガー ソルト&レモン",
            "calories": 499
        },
        {
            "name": "ビッグマック",
            "calories": 525
        },
        {
            "name": "炙り醤油風 ダブル肉厚ビーフ",
            "calories": 625
        },
        {
            "name": "炙り醤油風 ベーコントマト肉厚ビーフ",
            "calories": 471
        },
        {
            "name": "ダブルチーズバーガー",
            "calories": 457
        },
        {
            "name": "てりやきマックバーガー",
            "calories": 478
        },
        {
            "name": "フィレオフィッシュ",
            "calories": 326
        },
        {
            "name": "チキンフィレオ",
            "calories": 465
        },
        {
            "name": "てりやきチキンフィレオ",
            "calories": 498
        },
        {
            "name": "ベーコンレタスバーガー",
            "calories": 374
        },
        {
            "name": "えびフィレオ",
            "calories": 395
        },
        {
            "name": "スパチキ(スパイシーチキンバーガー)",
            "calories": 386
        },
        {
            "name": "スパビー(スパイシービーフバーガー)",
            "calories": 329
        },
        {
            "name": "エグチ(エッグチーズバーガー)",
            "calories": 387
        },
        {
            "name": "チキチー(チキンチーズバーガー)",
            "calories": 431
        },
        {
            "name": "ハンバーガー",
            "calories": 256
        },
        {
            "name": "チキンクリスプ",
            "calories": 345
        },
        {
            "name": "チーズバーガー",
            "calories": 307
        },
        {
            "name": "倍ビッグマック",
            "calories": 724
        },
        {
            "name": "倍ダブルチーズバーガー",
            "calories": 655
        },
        {
            "name": "倍てりやきマックバーガー",
            "calories": 728
        },
        {
            "name": "倍フィレオフィッシュ",
            "calories": 437
        },
        {
            "name": "倍チキンフィレオ",
            "calories": 709
        },
        {
            "name": "倍てりやきチキンフィレオ",
            "calories": 768
        },
        {
            "name": "倍ベーコンレタスバーガー",
            "calories": 473
        },
        {
            "name": "倍えびフィレオ",
            "calories": 553
        },
        {
            "name": "倍スパチキ(倍スパイシーチキンバーガー)",
            "calories": 538
        },
        {
            "name": "倍スパビー(倍スパイシービーフバーガー)",
            "calories": 428
        },
        {
            "name": "倍エグチ(倍エッグチーズバーガー)",
            "calories": 486
        },
        {
            "name": "倍チキチー(倍チキンチーズバーガー)",
            "calories": 584
        },
        {
            "name": "倍ハンバーガー",
            "calories": 356
        },
        {
            "name": "倍チキンクリスプ",
            "calories": 498
        },
        {
            "name": "倍チーズバーガー",
            "calories": 406
        },
        {
            "name": "エッグマックマフィン",
            "calories": 311
        },
        {
            "name": "ベーコンエッグマックサンド",
            "calories": 292
        },
        {
            "name": "ソーセージエッグマフィン",
            "calories": 475
        },
        {
            "name": "ソーセージマフィン",
            "calories": 395
        },
        {
            "name": "チキンクリスプマフィン",
            "calories": 364
        },
        {
            "name": "ホットケーキ",
            "calories": 322
        },
        {
            "name": "マックグリドル ソーセージエッグ",
            "calories": 550
        },
        {
            "name": "マックグリドル ベーコンエッグ",
            "calories": 396
        },
        {
            "name": "マックグリドル ソーセージ",
            "calories": 420
        },
        {
            "name": "メガマフィン",
            "calories": 695
        },
        {
            "name": "ビッグブレックファスト(ハッシュポテト含む)",
            "calories": 659
        },
        {
            "name": "ビッグブレックファスト デラックス(ハッシュポテト含む)",
            "calories": 982
        },
        {
            "name": "ストロベリージャム",
            "calories": 38
        },
        {
            "name": "塩・コショウ",
            "calories": 1
        },
        {
            "name": "バターパット",
            "calories": 60
        },
        {
            "name": "ホットケーキシロップ",
            "calories": 121
        }
    ]
}